{
  "runId": "20260205-120603-1706111",
  "iteration": "7",
  "mode": "build",
  "story": {
    "id": "US-007",
    "title": "Add write_markdown operation for append/prepend"
  },
  "started": "2026-02-05 13:13:30",
  "ended": "2026-02-05 13:23:12",
  "durationSeconds": 582,
  "status": "success",
  "log": "/home/hacker/Projects/Library-Service/.forge/logs/iter-07.raw.txt",
  "git": {
    "headBefore": "bac76e4e5bfe35bd010532b9bb7b194acee7e7e0",
    "headAfter": "23529964384ee2ce390a81b3feab9204d40f5ee1",
    "commits": [
      "2352996 chore(forge): update progress log",
      "4ad3db7 feat(mcp): add write_markdown append/prepend"
    ],
    "changedFiles": [
      ".agents/tasks/prd-markdown-mcp.json",
      ".forge/.tmp/prompt-20260205-120603-1706111-7.md",
      ".forge/.tmp/story-20260205-120603-1706111-7.json",
      ".forge/.tmp/story-20260205-120603-1706111-7.md",
      ".forge/activity.log",
      ".forge/errors.log",
      ".forge/events.jsonl",
      ".forge/iterations/iter-06.json",
      ".forge/logs/iter-06.raw.txt",
      ".forge/logs/iter-07.raw.txt",
      ".forge/metrics.json",
      ".forge/progress.md",
      ".forge/stories/US-006.json",
      ".forge/stories/US-007.json",
      ".forge/stories/US-008.json",
      ".forge/stories/US-009.json",
      ".forge/stories/US-010.json",
      ".forge/stories/US-011.json",
      ".forge/stories/US-012.json",
      ".forge/stories/US-013.json",
      "app/mcp.py",
      "tests/test_write_markdown.py"
    ],
    "dirtyFiles": [
      ".forge/activity.log",
      ".forge/events.jsonl",
      ".forge/logs/iter-07.raw.txt"
    ]
  },
  "updatedAt": "2026-02-05T18:23:13.862689+00:00"
}
